setup.cfg
setup.py
Slack_Webhooks.egg-info/PKG-INFO
Slack_Webhooks.egg-info/SOURCES.txt
Slack_Webhooks.egg-info/dependency_links.txt
Slack_Webhooks.egg-info/requires.txt
Slack_Webhooks.egg-info/top_level.txt
slack_webhooks/__init__.py
slack_webhooks/webhooks.py
slack_webhooks.egg-info/SOURCES.txt