Metadata-Version: 1.0
Name: slack-webhooks
Version: 1.0.6
Summary: Incoming Webhook helper for Slack
Home-page: https://github.com/jeffrand/slack-webhooks
Author: Jeff Rand
Author-email: jeffreyrand@gmail.com
License: UNKNOWN
Platform: UNKNOWN
